Metadata-Version: 1.0
Name: Probability-Distr
Version: 0.2
Summary: Gaussian and Binomial distributions
Home-page: UNKNOWN
Author: Opeyemi Ajala
Author-email: daelectropel@gmail.com
License: UNKNOWN
Platform: UNKNOWN
